fileformats/extras/medimage_afni/__init__.py
fileformats/extras/medimage_afni/_version.py
fileformats/extras/medimage_afni/tests/test_generate_sample_data.py
fileformats_medimage_afni_extras-0.4.1.dist-info/METADATA
fileformats_medimage_afni_extras-0.4.1.dist-info/WHEEL
fileformats_medimage_afni_extras-0.4.1.dist-info/licenses/LICENSE
fileformats_medimage_afni_extras-0.4.1.dist-info/RECORD
